MANIFEST.in
README.txt
plonetheme.colorcontext-configure.zcml
setup.cfg
setup.py
docs/HISTORY.txt
docs/INSTALL.txt
docs/LICENSE.GPL
docs/LICENSE.txt
plonetheme/.DS_Store
plonetheme/__init__.py
plonetheme.colorcontext.egg-info/PKG-INFO
plonetheme.colorcontext.egg-info/SOURCES.txt
plonetheme.colorcontext.egg-info/dependency_links.txt
plonetheme.colorcontext.egg-info/entry_points.txt
plonetheme.colorcontext.egg-info/namespace_packages.txt
plonetheme.colorcontext.egg-info/not-zip-safe
plonetheme.colorcontext.egg-info/paster_plugins.txt
plonetheme.colorcontext.egg-info/requires.txt
plonetheme.colorcontext.egg-info/top_level.txt
plonetheme/colorcontext/__init__.py
plonetheme/colorcontext/configure.zcml
plonetheme/colorcontext/profiles.zcml
plonetheme/colorcontext/setuphandlers.py
plonetheme/colorcontext/skins.zcml
plonetheme/colorcontext/tests.py
plonetheme/colorcontext/version.txt
plonetheme/colorcontext/Extensions/Install.py
plonetheme/colorcontext/browser/__init__.py
plonetheme/colorcontext/browser/classprovider.py
plonetheme/colorcontext/browser/collection_view.pt
plonetheme/colorcontext/browser/collection_view.py
plonetheme/colorcontext/browser/colorcontext_album_view.pt
plonetheme/colorcontext/browser/colorcontext_album_view.py
plonetheme/colorcontext/browser/colorcontext_image_view.pt
plonetheme/colorcontext/browser/colorcontext_image_view.py
plonetheme/colorcontext/browser/colorcontext_work_view.pt
plonetheme/colorcontext/browser/colorcontext_work_view.py
plonetheme/colorcontext/browser/configure.zcml
plonetheme/colorcontext/browser/configure.zcml.save
plonetheme/colorcontext/browser/flowplayer_file.pt
plonetheme/colorcontext/browser/flowplayer_file.pt.save
plonetheme/colorcontext/browser/flowplayer_view.py
plonetheme/colorcontext/browser/interfaces.py
plonetheme/colorcontext/browser/intk.pt
plonetheme/colorcontext/browser/menu.pt
plonetheme/colorcontext/browser/menuBAK.pt
plonetheme/colorcontext/browser/searchview.py
plonetheme/colorcontext/browser/viewlet.pt
plonetheme/colorcontext/browser/viewlets.py
plonetheme/colorcontext/browser/images/README.txt
plonetheme/colorcontext/browser/javascript/colorcontext.js
plonetheme/colorcontext/browser/stylesheets/README.txt
plonetheme/colorcontext/browser/stylesheets/main.css
plonetheme/colorcontext/profiles/default/cssregistry.xml
plonetheme/colorcontext/profiles/default/import_steps.xml
plonetheme/colorcontext/profiles/default/jsregistry.xml
