Metadata-Version: 1.0
Name: plonetheme.colorcontext
Version: 0.9
Summary: Total CSS rebuild and color themed sections
Home-page: https://svn.v2.nl/plone/plonetheme.colorcontext
Author: David Jonas
Author-email: david@v2.nl
License: GPL
Keywords: web zope plone theme
Platform: UNKNOWN
Classifier: Framework :: Plone
Classifier: Programming Language :: Python
Classifier: Topic :: Software Development :: Libraries :: Python Modules
